odoo/addons/ssi_task_code/README.rst
odoo/addons/ssi_task_code/__init__.py
odoo/addons/ssi_task_code/__manifest__.py
odoo/addons/ssi_task_code/hooks.py
odoo/addons/ssi_task_code/data/ir_sequence_data.xml
odoo/addons/ssi_task_code/data/sequence_template_data.xml
odoo/addons/ssi_task_code/models/__init__.py
odoo/addons/ssi_task_code/models/project_task.py
odoo/addons/ssi_task_code/static/description/icon.png
odoo/addons/ssi_task_code/views/project_task_views.xml
odoo14_addon_ssi_task_code-14.0.1.3.0.dist-info/METADATA
odoo14_addon_ssi_task_code-14.0.1.3.0.dist-info/WHEEL
odoo14_addon_ssi_task_code-14.0.1.3.0.dist-info/top_level.txt
odoo14_addon_ssi_task_code-14.0.1.3.0.dist-info/RECORD
